xmake/__init__.py
xmake/__main__.py
xmake/py.typed
xmake_wheel-2.9.9.data/data/lib/lua-cjson.lib
xmake_wheel-2.9.9.data/data/lib/lua.lib
xmake_wheel-2.9.9.data/data/lib/lz4.lib
xmake_wheel-2.9.9.data/data/lib/pdcurses.lib
xmake_wheel-2.9.9.data/data/lib/sv.lib
xmake_wheel-2.9.9.data/data/lib/tbox.lib
xmake_wheel-2.9.9.data/data/lib/xmake.lib
xmake_wheel-2.9.9.data/data/lib/cmake/libsv/libsvConfig.cmake
xmake_wheel-2.9.9.data/data/lib/cmake/libsv/libsvConfigVersion.cmake
xmake_wheel-2.9.9.data/data/lib/cmake/libsv/tboxTargets-release.cmake
xmake_wheel-2.9.9.data/data/lib/cmake/libsv/tboxTargets.cmake
xmake_wheel-2.9.9.data/data/lib/pkgconfig/tbox.pc
xmake_wheel-2.9.9.data/headers/lz4.h
xmake_wheel-2.9.9.data/headers/lz4file.h
xmake_wheel-2.9.9.data/headers/lz4frame.h
xmake_wheel-2.9.9.data/headers/lz4frame_static.h
xmake_wheel-2.9.9.data/headers/lz4hc.h
xmake_wheel-2.9.9.data/headers/semver.h
xmake_wheel-2.9.9.data/headers/xxhash.h
xmake_wheel-2.9.9.data/headers/lua/lapi.h
xmake_wheel-2.9.9.data/headers/lua/lauxlib.h
xmake_wheel-2.9.9.data/headers/lua/lcode.h
xmake_wheel-2.9.9.data/headers/lua/lctype.h
xmake_wheel-2.9.9.data/headers/lua/ldebug.h
xmake_wheel-2.9.9.data/headers/lua/ldo.h
xmake_wheel-2.9.9.data/headers/lua/lfunc.h
xmake_wheel-2.9.9.data/headers/lua/lgc.h
xmake_wheel-2.9.9.data/headers/lua/ljumptab.h
xmake_wheel-2.9.9.data/headers/lua/llex.h
xmake_wheel-2.9.9.data/headers/lua/llimits.h
xmake_wheel-2.9.9.data/headers/lua/lmem.h
xmake_wheel-2.9.9.data/headers/lua/lobject.h
xmake_wheel-2.9.9.data/headers/lua/lopcodes.h
xmake_wheel-2.9.9.data/headers/lua/lopnames.h
xmake_wheel-2.9.9.data/headers/lua/lparser.h
xmake_wheel-2.9.9.data/headers/lua/lprefix.h
xmake_wheel-2.9.9.data/headers/lua/lstate.h
xmake_wheel-2.9.9.data/headers/lua/lstring.h
xmake_wheel-2.9.9.data/headers/lua/ltable.h
xmake_wheel-2.9.9.data/headers/lua/ltests.h
xmake_wheel-2.9.9.data/headers/lua/ltm.h
xmake_wheel-2.9.9.data/headers/lua/lua.h
xmake_wheel-2.9.9.data/headers/lua/luaconf.h
xmake_wheel-2.9.9.dist-info/licenses/LICENSE
xmake_wheel-2.9.9.dist-info/WHEEL
xmake_wheel-2.9.9.dist-info/METADATA
xmake_wheel-2.9.9.dist-info/RECORD
