Metadata-Version: 2.4
Name: xmake-wheel
Version: 2.9.9
Summary: A cross-platform build utility based on Lua
Keywords: xmake
Author-email: ruki <waruqi@gmail.com>
Requires-Python: >= 3.10
Classifier: Development Status :: 3 - Alpha
Classifier: Intended Audience :: Developers
Classifier: Topic :: Software Development :: Build Tools
Classifier: License :: OSI Approved :: GNU General Public License v3 (GPLv3)
Classifier: Operating System :: Microsoft :: Windows
Classifier: Operating System :: POSIX
Classifier: Operating System :: Unix
Classifier: Operating System :: MacOS
Classifier: Programming Language :: Python :: 3 :: Only
Classifier: Programming Language :: Python :: 3
Classifier: Programming Language :: Python :: 3.10
Classifier: Programming Language :: Python :: 3.11
Classifier: Programming Language :: Python :: 3.12
Classifier: Programming Language :: Python :: Implementation :: CPython
Classifier: Programming Language :: Python :: Implementation :: PyPy
License-File: LICENSE
Project-URL: Bug Report, https://github.com/xmake-io/xmake-wheel/issues
Project-URL: Download, https://github.com/xmake-io/xmake-wheel/releases
Project-URL: Homepage, https://xmake-wheel.readthedocs.io
Project-URL: Source, https://github.com/xmake-io/xmake-wheel
